setup.py
sunnyday/__init__.py
sunnyday/sunnyday.py
sunnyday.egg-info/PKG-INFO
sunnyday.egg-info/SOURCES.txt
sunnyday.egg-info/dependency_links.txt
sunnyday.egg-info/requires.txt
sunnyday.egg-info/top_level.txt