Metadata-Version: 1.1
Name: sunnyday
Version: 1.0.0
Summary: Weather forecast data
Home-page: https://example.com
Author: Ardit Sulce
Author-email: your.email@example.com
License: MIT
Keywords: weather,forecast,openweather
Platform: UNKNOWN
Classifier: Development Status :: 3 - Alpha
Classifier: Intended Audience :: Developers
Classifier: Topic :: Software Development :: Build Tools
Classifier: License :: OSI Approved :: MIT License
Classifier: Programming Language :: Python :: 3.5
Classifier: Programming Language :: Python :: 3.6
Classifier: Programming Language :: Python :: 3.7
Classifier: Programming Language :: Python :: 3.8
